package/__Init__.py
package/error.py
package/validate.py
tinyinterror_dwu-0.1.1.dist-info/licenses/LICENSE.txt
tinyinterror_dwu-0.1.1.dist-info/METADATA
tinyinterror_dwu-0.1.1.dist-info/WHEEL
tinyinterror_dwu-0.1.1.dist-info/top_level.txt
tinyinterror_dwu-0.1.1.dist-info/RECORD
