Metadata-Version: 2.4
Name: tinyinterror_dwu
Version: 0.1.1
Summary: Este paquete nos permite validar errores de tipo tinyInt
Author: DWU
Author-email: desarrollos_web_urquiza@hotmail.com
License-File: LICENSE.txt
Dynamic: author
Dynamic: author-email
Dynamic: license-file
Dynamic: summary
